unilogin/__init__.py
unilogin-0.0.3.dist-info/LICENSE
unilogin-0.0.3.dist-info/METADATA
unilogin-0.0.3.dist-info/WHEEL
unilogin-0.0.3.dist-info/top_level.txt
unilogin-0.0.3.dist-info/RECORD
