Metadata-Version: 2.1
Name: unilogin
Version: 0.0.3
Summary: Log ind på alle sider som bruger unilogin kun ved brug af python
Home-page: https://github.com/jona799t/unilogin-api
Author: jona799t
License: UNKNOWN
Keywords: python,unilogin,uni-login,skole
Platform: UNKNOWN
Classifier: Development Status :: 1 - Planning
Classifier: Intended Audience :: Developers
Classifier: Programming Language :: Python :: 3
Classifier: Operating System :: Unix
Classifier: Operating System :: MacOS :: MacOS X
Classifier: Operating System :: Microsoft :: Windows
Requires-Dist: bs4
Requires-Dist: httpx (==0.22.0)
